MANIFEST.in
README.rst
setup.cfg
setup.py
trionyx_accounts/__init__.py
trionyx_accounts/apps.py
trionyx_accounts/conf.py
trionyx_accounts/forms.py
trionyx_accounts/layouts.py
trionyx_accounts/models.py
trionyx_accounts.egg-info/PKG-INFO
trionyx_accounts.egg-info/SOURCES.txt
trionyx_accounts.egg-info/dependency_links.txt
trionyx_accounts.egg-info/entry_points.txt
trionyx_accounts.egg-info/requires.txt
trionyx_accounts.egg-info/top_level.txt
trionyx_accounts/locale/en_US/LC_MESSAGES/django.mo
trionyx_accounts/locale/en_US/LC_MESSAGES/django.po
trionyx_accounts/locale/nl_NL/LC_MESSAGES/django.mo
trionyx_accounts/locale/nl_NL/LC_MESSAGES/django.po
trionyx_accounts/migrations/0001_initial.py
trionyx_accounts/migrations/0002_auto_20201005_1143.py
trionyx_accounts/migrations/__init__.py